{
    "os": "Linux-5.15.0-130-generic-x86_64-with-glibc2.35",
    "python": "3.10.13",
    "heartbeatAt": "2025-05-09T01:44:07.237104",
    "startedAt": "2025-05-09T01:44:06.690290",
    "docker": null,
    "cuda": null,
    "args": [
        "--local_rank=0",
        "--version=liuhaotian/llava-llama-2-13b-chat-lightning-preview",
        "--dataset_dir=/shared/nas/data/m1/jk100/code/OpenAttrLibrary/LISA/dataset",
        "--vision_pretrained=/shared/nas/data/m1/jk100/code/OpenAttrLibrary/LISA/weights/sam_vit_h_4b8939.pth",
        "--zero_shot_ckpt_path=runs/plum-13b_kld_0.1_focal_tversky_8_v1_0shot/plum-13b_kld_0.1_focal_tversky_8_v1_0shot_bidirbio_2048_accum_10_maxlen512_epochs25_segloss_2_bce_loss_2_kld_loss_0_dice_loss_8_bidir_bio_train_prompt_enc_ckpt_model",
        "--dataset=explanatory_seg",
        "--explanatory_seg_data",
        "--partonomy_dataset_split=partimagenet|pascal_part|paco_lvis",
        "--sample_one_question_per_image",
        "--random_seed=42",
        "--sample_rates=1",
        "--batch_size=6",
        "--grad_accumulation_steps",
        "10",
        "--ce_loss_weight=1.0",
        "--dice_type=focal_tversky",
        "--dice_loss_weight=8",
        "--bce_loss_weight=2.0",
        "--kld_loss_weight=0.1",
        "--seg_cls_loss_weight=2",
        "--exp_name=plum-13b_kld_0.1_focal_tversky_8_v1_partonomy_ft",
        "--precision=bf16",
        "--model_max_length",
        "512",
        "--dice_scale_factor",
        "1000.0",
        "--epochs",
        "20",
        "--train_mask_prompt_encoder",
        "--use_bidir_bio",
        "--focal_tversky_alpha=0.7",
        "--focal_tversky_beta=0.3",
        "--bidir_dim_feedforward",
        "2048",
        "--lr",
        "3e-4",
        "--auto_resume"
    ],
    "state": "running",
    "program": "/shared/nas2/jk100/partonomy_private/src/models/PLUM/plum_train_ds.py",
    "codePathLocal": "plum_train_ds.py",
    "codePath": "src/models/PLUM/plum_train_ds.py",
    "git": {
        "remote": "https://github.com/AnselBlume/partonomy_private.git",
        "commit": "803bca9401deab7c9b870c6a5bd0c6e83d9743f0"
    },
    "email": "jeonghwankim123@gmail.com",
    "root": "/shared/nas2/jk100/partonomy_private",
    "host": "blender13.cs.illinois.edu",
    "username": "jk100",
    "executable": "/shared/nas/data/m1/jk100/.conda/envs/llava/bin/python",
    "cpu_count": 64,
    "cpu_count_logical": 128,
    "cpu_freq": {
        "current": 2924.530546875,
        "min": 0.0,
        "max": 0.0
    },
    "cpu_freq_per_core": [
        {
            "current": 3000.0,
            "min": 0.0,
            "max": 0.0
        },
        {
            "current": 2960.213,
            "min": 0.0,
            "max": 0.0
        },
        {
            "current": 3000.0,
            "min": 0.0,
            "max": 0.0
        },
        {
            "current": 2999.036,
            "min": 0.0,
            "max": 0.0
        },
        {
            "current": 2998.992,
            "min": 0.0,
            "max": 0.0
        },
        {
            "current": 2996.57,
            "min": 0.0,
            "max": 0.0
        },
        {
            "current": 3000.0,
            "min": 0.0,
            "max": 0.0
        },
        {
            "current": 2999.028,
            "min": 0.0,
            "max": 0.0
        },
        {
            "current": 2999.06,
            "min": 0.0,
            "max": 0.0
        },
        {
            "current": 2964.462,
            "min": 0.0,
            "max": 0.0
        },
        {
            "current": 2997.265,
            "min": 0.0,
            "max": 0.0
        },
        {
            "current": 2960.748,
            "min": 0.0,
            "max": 0.0
        },
        {
            "current": 2999.273,
            "min": 0.0,
            "max": 0.0
        },
        {
            "current": 2998.533,
            "min": 0.0,
            "max": 0.0
        },
        {
            "current": 3000.0,
            "min": 0.0,
            "max": 0.0
        },
        {
            "current": 2959.427,
            "min": 0.0,
            "max": 0.0
        },
        {
            "current": 2999.267,
            "min": 0.0,
            "max": 0.0
        },
        {
            "current": 2999.03,
            "min": 0.0,
            "max": 0.0
        },
        {
            "current": 3000.0,
            "min": 0.0,
            "max": 0.0
        },
        {
            "current": 3000.0,
            "min": 0.0,
            "max": 0.0
        },
        {
            "current": 2999.997,
            "min": 0.0,
            "max": 0.0
        },
        {
            "current": 2962.24,
            "min": 0.0,
            "max": 0.0
        },
        {
            "current": 3000.0,
            "min": 0.0,
            "max": 0.0
        },
        {
            "current": 2958.8,
            "min": 0.0,
            "max": 0.0
        },
        {
            "current": 2999.842,
            "min": 0.0,
            "max": 0.0
        },
        {
            "current": 2999.034,
            "min": 0.0,
            "max": 0.0
        },
        {
            "current": 3000.0,
            "min": 0.0,
            "max": 0.0
        },
        {
            "current": 2999.073,
            "min": 0.0,
            "max": 0.0
        },
        {
            "current": 2961.847,
            "min": 0.0,
            "max": 0.0
        },
        {
            "current": 2998.991,
            "min": 0.0,
            "max": 0.0
        },
        {
            "current": 2960.783,
            "min": 0.0,
            "max": 0.0
        },
        {
            "current": 2964.684,
            "min": 0.0,
            "max": 0.0
        },
        {
            "current": 2994.683,
            "min": 0.0,
            "max": 0.0
        },
        {
            "current": 2999.122,
            "min": 0.0,
            "max": 0.0
        },
        {
            "current": 3000.0,
            "min": 0.0,
            "max": 0.0
        },
        {
            "current": 2100.0,
            "min": 0.0,
            "max": 0.0
        },
        {
            "current": 3000.0,
            "min": 0.0,
            "max": 0.0
        },
        {
            "current": 2963.189,
            "min": 0.0,
            "max": 0.0
        },
        {
            "current": 3000.0,
            "min": 0.0,
            "max": 0.0
        },
        {
            "current": 2959.648,
            "min": 0.0,
            "max": 0.0
        },
        {
            "current": 2999.105,
            "min": 0.0,
            "max": 0.0
        },
        {
            "current": 2100.0,
            "min": 0.0,
            "max": 0.0
        },
        {
            "current": 2999.562,
            "min": 0.0,
            "max": 0.0
        },
        {
            "current": 2998.362,
            "min": 0.0,
            "max": 0.0
        },
        {
            "current": 3000.0,
            "min": 0.0,
            "max": 0.0
        },
        {
            "current": 2998.228,
            "min": 0.0,
            "max": 0.0
        },
        {
            "current": 2960.718,
            "min": 0.0,
            "max": 0.0
        },
        {
            "current": 2962.982,
            "min": 0.0,
            "max": 0.0
        },
        {
            "current": 2999.904,
            "min": 0.0,
            "max": 0.0
        },
        {
            "current": 2999.0,
            "min": 0.0,
            "max": 0.0
        },
        {
            "current": 3000.0,
            "min": 0.0,
            "max": 0.0
        },
        {
            "current": 2999.154,
            "min": 0.0,
            "max": 0.0
        },
        {
            "current": 3000.0,
            "min": 0.0,
            "max": 0.0
        },
        {
            "current": 2999.29,
            "min": 0.0,
            "max": 0.0
        },
        {
            "current": 3000.0,
            "min": 0.0,
            "max": 0.0
        },
        {
            "current": 2960.875,
            "min": 0.0,
            "max": 0.0
        },
        {
            "current": 2999.997,
            "min": 0.0,
            "max": 0.0
        },
        {
            "current": 3000.005,
            "min": 0.0,
            "max": 0.0
        },
        {
            "current": 2999.838,
            "min": 0.0,
            "max": 0.0
        },
        {
            "current": 2994.581,
            "min": 0.0,
            "max": 0.0
        },
        {
            "current": 3000.002,
            "min": 0.0,
            "max": 0.0
        },
        {
            "current": 2958.138,
            "min": 0.0,
            "max": 0.0
        },
        {
            "current": 2997.36,
            "min": 0.0,
            "max": 0.0
        },
        {
            "current": 2998.896,
            "min": 0.0,
            "max": 0.0
        },
        {
            "current": 3000.0,
            "min": 0.0,
            "max": 0.0
        },
        {
            "current": 2955.505,
            "min": 0.0,
            "max": 0.0
        },
        {
            "current": 3000.0,
            "min": 0.0,
            "max": 0.0
        },
        {
            "current": 2998.814,
            "min": 0.0,
            "max": 0.0
        },
        {
            "current": 2998.824,
            "min": 0.0,
            "max": 0.0
        },
        {
            "current": 2995.726,
            "min": 0.0,
            "max": 0.0
        },
        {
            "current": 2999.997,
            "min": 0.0,
            "max": 0.0
        },
        {
            "current": 2998.662,
            "min": 0.0,
            "max": 0.0
        },
        {
            "current": 2998.908,
            "min": 0.0,
            "max": 0.0
        },
        {
            "current": 2959.288,
            "min": 0.0,
            "max": 0.0
        },
        {
            "current": 2996.842,
            "min": 0.0,
            "max": 0.0
        },
        {
            "current": 2959.984,
            "min": 0.0,
            "max": 0.0
        },
        {
            "current": 2999.155,
            "min": 0.0,
            "max": 0.0
        },
        {
            "current": 2998.758,
            "min": 0.0,
            "max": 0.0
        },
        {
            "current": 3000.0,
            "min": 0.0,
            "max": 0.0
        },
        {
            "current": 2953.663,
            "min": 0.0,
            "max": 0.0
        },
        {
            "current": 2999.164,
            "min": 0.0,
            "max": 0.0
        },
        {
            "current": 2998.903,
            "min": 0.0,
            "max": 0.0
        },
        {
            "current": 3000.0,
            "min": 0.0,
            "max": 0.0
        },
        {
            "current": 3000.002,
            "min": 0.0,
            "max": 0.0
        },
        {
            "current": 3000.0,
            "min": 0.0,
            "max": 0.0
        },
        {
            "current": 2957.457,
            "min": 0.0,
            "max": 0.0
        },
        {
            "current": 3000.0,
            "min": 0.0,
            "max": 0.0
        },
        {
            "current": 2958.993,
            "min": 0.0,
            "max": 0.0
        },
        {
            "current": 2999.817,
            "min": 0.0,
            "max": 0.0
        },
        {
            "current": 2998.95,
            "min": 0.0,
            "max": 0.0
        },
        {
            "current": 3000.0,
            "min": 0.0,
            "max": 0.0
        },
        {
            "current": 2998.971,
            "min": 0.0,
            "max": 0.0
        },
        {
            "current": 2925.608,
            "min": 0.0,
            "max": 0.0
        },
        {
            "current": 2999.015,
            "min": 0.0,
            "max": 0.0
        },
        {
            "current": 2958.293,
            "min": 0.0,
            "max": 0.0
        },
        {
            "current": 2960.145,
            "min": 0.0,
            "max": 0.0
        },
        {
            "current": 2994.184,
            "min": 0.0,
            "max": 0.0
        },
        {
            "current": 2998.298,
            "min": 0.0,
            "max": 0.0
        },
        {
            "current": 3000.0,
            "min": 0.0,
            "max": 0.0
        },
        {
            "current": 2999.122,
            "min": 0.0,
            "max": 0.0
        },
        {
            "current": 3000.0,
            "min": 0.0,
            "max": 0.0
        },
        {
            "current": 2960.157,
            "min": 0.0,
            "max": 0.0
        },
        {
            "current": 3000.0,
            "min": 0.0,
            "max": 0.0
        },
        {
            "current": 2999.615,
            "min": 0.0,
            "max": 0.0
        },
        {
            "current": 2100.0,
            "min": 0.0,
            "max": 0.0
        },
        {
            "current": 2999.795,
            "min": 0.0,
            "max": 0.0
        },
        {
            "current": 2100.0,
            "min": 0.0,
            "max": 0.0
        },
        {
            "current": 2999.232,
            "min": 0.0,
            "max": 0.0
        },
        {
            "current": 2100.0,
            "min": 0.0,
            "max": 0.0
        },
        {
            "current": 2998.308,
            "min": 0.0,
            "max": 0.0
        },
        {
            "current": 2100.0,
            "min": 0.0,
            "max": 0.0
        },
        {
            "current": 2997.334,
            "min": 0.0,
            "max": 0.0
        },
        {
            "current": 2100.0,
            "min": 0.0,
            "max": 0.0
        },
        {
            "current": 2998.723,
            "min": 0.0,
            "max": 0.0
        },
        {
            "current": 2999.213,
            "min": 0.0,
            "max": 0.0
        },
        {
            "current": 3000.0,
            "min": 0.0,
            "max": 0.0
        },
        {
            "current": 2100.0,
            "min": 0.0,
            "max": 0.0
        },
        {
            "current": 2999.424,
            "min": 0.0,
            "max": 0.0
        },
        {
            "current": 2999.468,
            "min": 0.0,
            "max": 0.0
        },
        {
            "current": 2999.278,
            "min": 0.0,
            "max": 0.0
        },
        {
            "current": 3000.0,
            "min": 0.0,
            "max": 0.0
        },
        {
            "current": 3000.0,
            "min": 0.0,
            "max": 0.0
        },
        {
            "current": 3000.0,
            "min": 0.0,
            "max": 0.0
        },
        {
            "current": 2998.234,
            "min": 0.0,
            "max": 0.0
        },
        {
            "current": 3000.002,
            "min": 0.0,
            "max": 0.0
        },
        {
            "current": 2998.675,
            "min": 0.0,
            "max": 0.0
        },
        {
            "current": 2100.0,
            "min": 0.0,
            "max": 0.0
        },
        {
            "current": 2999.305,
            "min": 0.0,
            "max": 0.0
        }
    ],
    "disk": {
        "/": {
            "total": 428.1472702026367,
            "used": 263.38611221313477
        }
    },
    "gpu": "NVIDIA A100-SXM4-80GB",
    "gpu_count": 8,
    "gpu_devices": [
        {
            "name": "NVIDIA A100-SXM4-80GB",
            "memory_total": 85899345920
        },
        {
            "name": "NVIDIA A100-SXM4-80GB",
            "memory_total": 85899345920
        },
        {
            "name": "NVIDIA A100-SXM4-80GB",
            "memory_total": 85899345920
        },
        {
            "name": "NVIDIA A100-SXM4-80GB",
            "memory_total": 85899345920
        },
        {
            "name": "NVIDIA A100-SXM4-80GB",
            "memory_total": 85899345920
        },
        {
            "name": "NVIDIA A100-SXM4-80GB",
            "memory_total": 85899345920
        },
        {
            "name": "NVIDIA A100-SXM4-80GB",
            "memory_total": 85899345920
        },
        {
            "name": "NVIDIA A100-SXM4-80GB",
            "memory_total": 85899345920
        }
    ],
    "memory": {
        "total": 1007.3798370361328
    }
}
